odoo/addons/account_invoice_outstanding_credit/LICENSE
odoo/addons/account_invoice_outstanding_credit/README.rst
odoo/addons/account_invoice_outstanding_credit/__init__.py
odoo/addons/account_invoice_outstanding_credit/__manifest__.py
odoo/addons/account_invoice_outstanding_credit/i18n/de_CH.po
odoo/addons/account_invoice_outstanding_credit/images/screen.png
odoo/addons/account_invoice_outstanding_credit/models/__init__.py
odoo/addons/account_invoice_outstanding_credit/models/account_move.py
odoo/addons/account_invoice_outstanding_credit/static/description/icon.png
odoo/addons/account_invoice_outstanding_credit/static/description/index.html
odoo/addons/account_invoice_outstanding_credit/tests/TEST_INSTRUCTIONS.rst
odoo/addons/account_invoice_outstanding_credit/views/account_move.xml
odoo_addon_account_invoice_outstanding_credit-18.0.1.0.0.dist-info/METADATA
odoo_addon_account_invoice_outstanding_credit-18.0.1.0.0.dist-info/WHEEL
odoo_addon_account_invoice_outstanding_credit-18.0.1.0.0.dist-info/top_level.txt
odoo_addon_account_invoice_outstanding_credit-18.0.1.0.0.dist-info/RECORD
